LICENSE.txt
README.md
VERSION.txt
session-file.json
osve/__init__.py
osve/eps_utils.py
osve/osve.py
osve/osve_cmd.py
osve/osve_subscriber.py
osve/session_file.py
osve/utils.py
osve/deliveries/lin/libosve-if.so
osve/deliveries/mac/arm64/libosve-if.dylib
osve/deliveries/mac/x86_64/libosve-if.dylib
osve/deliveries/win/osve-if.dll
osve/subscribers/__init__.py
osve/subscribers/external_constraint_abstract.py
osve/subscribers/osve_datapack.py
osve/subscribers/osve_event_subscriber.py
osve/subscribers/osve_files.py
osve/subscribers/osve_idle_subscriber.py
osve/subscribers/osve_logger_abstract.py
osve/subscribers/osve_ptr_abstract.py
osve/subscribers/osve_ptr_logger.py
osve/subscribers/osve_subscriber_abstract.py
osve-2.7.1.dist-info/LICENSE.txt
osve-2.7.1.dist-info/METADATA
osve-2.7.1.dist-info/WHEEL
osve-2.7.1.dist-info/entry_points.txt
osve-2.7.1.dist-info/top_level.txt
osve-2.7.1.dist-info/RECORD
