Metadata-Version: 2.1
Name: osve
Version: 2.7.1
Summary: Python package for OSVE
Home-page: https://gitlab.esa.int/juice-soc/juice-uplink/spm/phs/osve
Author: Ricardo Valles, Marc Costa
Author-email: juice_soc@sciops.esa.int
License: UNKNOWN
Keywords: esa,Juice,AGM,EPS,planetary,space,metrics,trajectory,assessment,crema
Platform: Linux
Platform: MacOS
Classifier: Development Status :: 3 - Alpha
Requires-Python: >=3.8
